chess_com_api/__init__.py
chess_com_api/_version.py
chess_com_api/client.py
chess_com_api/exceptions.py
chess_com_api/models.py
chess_com_api/utils.py
chess_com_api-1.0.0.dist-info/METADATA
chess_com_api-1.0.0.dist-info/WHEEL
chess_com_api-1.0.0.dist-info/licenses/LICENSE
chess_com_api-1.0.0.dist-info/RECORD
